README.md
setup.py
vee/__about__.py
vee/__init__.py
vee/__main__.py
vee/cli.py
vee/config.py
vee/database.py
vee/devpackage.py
vee/environment.py
vee/environmentrepo.py
vee/envvars.py
vee/exceptions.py
vee/git.py
vee/globals.py
vee/home.py
vee/homebrew.py
vee/libs.py
vee/lockfile.py
vee/log.py
vee/network.py
vee/package.py
vee/packageset.py
vee/requirements.py
vee/semver.py
vee/subproc.py
vee/utils.py
vee.egg-info/PKG-INFO
vee.egg-info/SOURCES.txt
vee.egg-info/dependency_links.txt
vee.egg-info/entry_points.txt
vee.egg-info/requires.txt
vee.egg-info/top_level.txt
vee/_bootstrap/__init__.py
vee/_bootstrap/get-pip.py
vee/commands/__init__.py
vee/commands/add.py
vee/commands/brew.py
vee/commands/client.py
vee/commands/commit.py
vee/commands/config.py
vee/commands/develop.py
vee/commands/doctor.py
vee/commands/edit.py
vee/commands/exec_.py
vee/commands/gc.py
vee/commands/git.py
vee/commands/init.py
vee/commands/install.py
vee/commands/link.py
vee/commands/list.py
vee/commands/main.py
vee/commands/push.py
vee/commands/relocate.py
vee/commands/repackage.py
vee/commands/repo.py
vee/commands/self_update.py
vee/commands/server.py
vee/commands/sqlite3.py
vee/commands/status.py
vee/commands/update.py
vee/commands/upgrade.py
vee/distutils/__init__.py
vee/distutils/vee_develop.py
vee/pipeline/__init__.py
vee/pipeline/archive.py
vee/pipeline/base.py
vee/pipeline/deferred.py
vee/pipeline/file.py
vee/pipeline/gem.py
vee/pipeline/generic.py
vee/pipeline/git.py
vee/pipeline/homebrew.py
vee/pipeline/http.py
vee/pipeline/make.py
vee/pipeline/pypi.py
vee/pipeline/python.py
vee/pipeline/rpm.py
vee/pipeline/self.py