Metadata-Version: 1.1
Name: vee
Version: 1.0.0.dev0
Summary: Versioned Execution Environments
Home-page: http://github.com/vfxetc/vee
Author: Mike Boers
Author-email: vee@mikeboers.com
License: BSD-3
Platform: UNKNOWN
Classifier: Intended Audience :: Developers
Classifier: Intended Audience :: System Administrators
Classifier: License :: OSI Approved :: BSD License
Classifier: Natural Language :: English
Classifier: Operating System :: OS Independent
Classifier: Programming Language :: Python :: 3.6
Classifier: Topic :: Software Development :: Build Tools
Classifier: Topic :: Software Development :: Version Control
Classifier: Topic :: System :: Installation/Setup
Classifier: Topic :: System :: Software Distribution
